rolling_snapshot_proposal_editor/.DS_Store
rolling_snapshot_proposal_editor/__init__.py
rolling_snapshot_proposal_editor/_find_lastline.py
rolling_snapshot_proposal_editor/_list_visits.py
rolling_snapshot_proposal_editor/add_fixed_target.py
rolling_snapshot_proposal_editor/add_visit.py
rolling_snapshot_proposal_editor/find_targetname_in_targetlist.py
rolling_snapshot_proposal_editor/find_targetname_in_visits.py
rolling_snapshot_proposal_editor/get_available_visitnumber.py
rolling_snapshot_proposal_editor/googlesheetreader.py
rolling_snapshot_proposal_editor/prepare_targetinfo.py
rolling_snapshot_proposal_editor/prop_profiling.py
rolling_snapshot_proposal_editor/remove_fixed_target.py
rolling_snapshot_proposal_editor/remove_visit.py
rolling_snapshot_proposal_editor/templatehandler.py
rolling_snapshot_proposal_editor/update_status_RN.py
rolling_snapshot_proposal_editor/update_status_SC.py
rolling_snapshot_proposal_editor/update_targetlist_from_sheet.py
rolling_snapshot_proposal_editor/update_visits_from_sheet.py
rolling_snapshot_proposal_editor/.ipynb_checkpoints/_find_lastline-checkpoint.py
rolling_snapshot_proposal_editor/.ipynb_checkpoints/_list_visits-checkpoint.py
rolling_snapshot_proposal_editor/.ipynb_checkpoints/add_fixed_target-checkpoint.py
rolling_snapshot_proposal_editor/.ipynb_checkpoints/add_visit-checkpoint.py
rolling_snapshot_proposal_editor/.ipynb_checkpoints/find_targetname_in_targetlist-checkpoint.py
rolling_snapshot_proposal_editor/.ipynb_checkpoints/find_targetname_in_visits-checkpoint.py
rolling_snapshot_proposal_editor/.ipynb_checkpoints/get_available_visitnumber-checkpoint.py
rolling_snapshot_proposal_editor/.ipynb_checkpoints/googlesheetreader-checkpoint.py
rolling_snapshot_proposal_editor/.ipynb_checkpoints/prepare_targetinfo-checkpoint.py
rolling_snapshot_proposal_editor/.ipynb_checkpoints/prop_profiling-checkpoint.py
rolling_snapshot_proposal_editor/.ipynb_checkpoints/remove_fixed_target-checkpoint.py
rolling_snapshot_proposal_editor-1.2.0.dist-info/LICENSE
rolling_snapshot_proposal_editor-1.2.0.dist-info/METADATA
rolling_snapshot_proposal_editor-1.2.0.dist-info/WHEEL
rolling_snapshot_proposal_editor-1.2.0.dist-info/top_level.txt
rolling_snapshot_proposal_editor-1.2.0.dist-info/RECORD
