Metadata-Version: 2.1
Name: rolling-snapshot-proposal-editor
Version: 1.2.0
Summary: UNKNOWN
Home-page: https://github.com/bkornpob/Rolling-Snapshot-Proposal-Editor.git
Author: Kornpob Bhirombhakdi
Author-email: kbhirombhakdi@stsci.edu
License: UNKNOWN
Platform: UNKNOWN
Classifier: Programming Language :: Python :: 3
Classifier: License :: OSI Approved :: MIT License
Classifier: Operating System :: OS Independent
Requires-Python: >=3.
